Metadata-Version: 1.0
Name: sonLib
Version: 1.1.0
Summary: Small general purpose library for C and Python with focus on bioinformatics.
Home-page: https://github.com/benedictpaten/sonLib
Author: Benedict Paten
Author-email: benedict@soe.ucsc.edu
License: UNKNOWN
Platform: UNKNOWN
